[{"index":0,"red":0,"green":0,"blue":0,"name":"empty"},{"index":1,"red":255,"green":52,"blue":39,"name":"descending corticofugal pathways"},{"index":2,"red":255,"green":186,"blue":0,"name":"substantia nigra"},{"index":3,"red":0,"green":0,"blue":255,"name":"subthalamic nucleus"},{"index":4,"red":255,"green":255,"blue":0,"name":"molecular layer of the cerebellum"},{"index":5,"red":0,"green":255,"blue":255,"name":"granule cell level of the cerebellum"},{"index":6,"red":255,"green":0,"blue":255,"name":"alveus of the hippocampus"},{"index":7,"red":52,"green":255,"blue":13,"name":"inferior cerebellar peduncle"},{"index":8,"red":29,"green":104,"blue":235,"name":"cingulate cortex, area 2"},{"index":9,"red":129,"green":79,"blue":255,"name":"striatum"},{"index":10,"red":255,"green":145,"blue":186,"name":"globus pallidus"},{"index":11,"red":26,"green":231,"blue":255,"name":"entopeduncular nucleus"},{"index":12,"red":2,"green":44,"blue":255,"name":"ventricular system"},{"index":13,"red":212,"green":255,"blue":0,"name":"medial lemniscus"},{"index":14,"red":255,"green":25,"blue":240,"name":"facial nerve"},{"index":15,"red":124,"green":252,"blue":0,"name":"anterior commissure, anterior part"},{"index":16,"red":255,"green":186,"blue":0,"name":"anterior commissure, posterior part"},{"index":17,"red":174,"green":0,"blue":232,"name":"ventral hippocampal commissure"},{"index":18,"red":0,"green":100,"blue":0,"name":"thalamus"},{"index":19,"red":255,"green":8,"blue":0,"name":"septal region"},{"index":20,"red":48,"green":218,"blue":0,"name":"optic nerve"},{"index":21,"red":38,"green":126,"blue":255,"name":"optic tract and optic chiasm"},{"index":22,"red":218,"green":170,"blue":62,"name":"pineal gland"},{"index":23,"red":134,"green":255,"blue":90,"name":"spinal cord"},{"index":24,"red":33,"green":230,"blue":255,"name":"commissure of the superior colliculus"},{"index":25,"red":153,"green":83,"blue":255,"name":"brainstem"},{"index":26,"red":226,"green":120,"blue":161,"name":"hypothalamic region"},{"index":27,"red":86,"green":0,"blue":221,"name":"superficial gray layer of the superior colliculus"},{"index":28,"red":7,"green":255,"blue":89,"name":"periaqueductal gray"},{"index":29,"red":21,"green":192,"blue":255,"name":"fornix"},{"index":30,"red":238,"green":186,"blue":0,"name":"mammillothalamic tract"},{"index":31,"red":173,"green":255,"blue":47,"name":"commissural stria terminalis"},{"index":32,"red":225,"green":151,"blue":15,"name":"deeper layers of the superior colliculus"},{"index":33,"red":235,"green":87,"blue":255,"name":"periventricular gray"},{"index":34,"red":250,"green":244,"blue":247,"name":"genu of the facial nerve"},{"index":35,"red":0,"green":215,"blue":11,"name":"pontine nuclei"},{"index":36,"red":0,"green":255,"blue":29,"name":"fimbria of the hippocampus"},{"index":37,"red":244,"green":67,"blue":69,"name":"fasciculus retroflexus"},{"index":38,"red":0,"green":255,"blue":0,"name":"stria medullaris of the thalamus"},{"index":39,"red":238,"green":117,"blue":51,"name":"stria terminalis"},{"index":40,"red":255,"green":0,"blue":218,"name":"posterior commissure"},{"index":41,"red":15,"green":109,"blue":230,"name":"glomerular layer of the accessory olfactory bulb"},{"index":42,"red":255,"green":227,"blue":0,"name":"glomerular layer of the olfactory bulb"},{"index":43,"red":255,"green":135,"blue":0,"name":"olfactory bulb"},{"index":44,"red":255,"green":110,"blue":0,"name":"corpus callosum and associated subcortical white matter"},{"index":45,"red":188,"green":32,"blue":173,"name":"brachium of the superior colliculus"},{"index":46,"red":255,"green":42,"blue":39,"name":"inferior colliculus, commissure"},{"index":47,"red":39,"green":244,"blue":253,"name":"central canal"},{"index":48,"red":63,"green":192,"blue":255,"name":"interpeduncular nucleus"},{"index":49,"red":179,"green":28,"blue":53,"name":"ascending fibers of the facial nerve"},{"index":50,"red":255,"green":79,"blue":206,"name":"anterior commissure"},{"index":51,"red":0,"green":246,"blue":14,"name":"inferior olive"},{"index":52,"red":91,"green":241,"blue":255,"name":"spinal trigeminal nucleus"},{"index":53,"red":250,"green":128,"blue":114,"name":"spinal trigeminal tract"},{"index":54,"red":206,"green":211,"blue":7,"name":"frontal association cortex"},{"index":55,"red":134,"green":204,"blue":76,"name":"middle cerebellar peduncle"},{"index":56,"red":128,"green":170,"blue":255,"name":"transverse fibers of the pons"},{"index":57,"red":69,"green":235,"blue":202,"name":"habenular commissure"},{"index":58,"red":222,"green":7,"blue":237,"name":"nucleus of the stria medullaris"},{"index":59,"red":225,"green":240,"blue":13,"name":"basal forebrain region"},{"index":60,"red":250,"green":170,"blue":64,"name":"supraoptic decussation"},{"index":61,"red":65,"green":150,"blue":255,"name":"medial lemniscus decussation"},{"index":62,"red":114,"green":9,"blue":212,"name":"pyramidal decussation"},{"index":63,"red":3,"green":193,"blue":45,"name":"neocortex"},{"index":64,"red":0,"green":8,"blue":182,"name":"bed nucleus of the stria terminalis"},{"index":65,"red":255,"green":87,"blue":30,"name":"pretectal region"},{"index":66,"red":165,"green":131,"blue":107,"name":"cornu ammonis 3"},{"index":67,"red":91,"green":45,"blue":10,"name":"dentate gyrus"},{"index":68,"red":255,"green":255,"blue":0,"name":"cornu ammonis 2"},{"index":69,"red":217,"green":104,"blue":13,"name":"cornu ammonis 1"},{"index":70,"red":255,"green":0,"blue":0,"name":"fasciola cinereum"},{"index":71,"red":255,"green":192,"blue":0,"name":"subiculum"},{"index":72,"red":40,"green":112,"blue":130,"name":"postrhinal cortex"},{"index":73,"red":80,"green":123,"blue":175,"name":"presubiculum"},{"index":74,"red":23,"green":54,"blue":96,"name":"parasubiculum"},{"index":75,"red":205,"green":51,"blue":255,"name":"perirhinal area 35"},{"index":76,"red":112,"green":48,"blue":160,"name":"perirhinal area 36"},{"index":77,"red":122,"green":187,"blue":51,"name":"entorhinal cortex"},{"index":78,"red":90,"green":111,"blue":47,"name":"lateral entorhinal cortex"},{"index":79,"red":0,"green":144,"blue":55,"name":"vestibular apparatus"},{"index":80,"red":0,"green":255,"blue":29,"name":"cochlea"},{"index":81,"red":253,"green":148,"blue":0,"name":"cochlear nerve"},{"index":82,"red":253,"green":50,"blue":0,"name":"vestibular nerve"},{"index":83,"red":0,"green":12,"blue":255,"name":"ventral cochlear nucleus, granule cell layer"},{"index":84,"red":52,"green":29,"blue":144,"name":"4th ventricle"},{"index":85,"red":92,"green":156,"blue":211,"name":"dorsal cochlear nucleus, molecular layer"},{"index":86,"red":0,"green":80,"blue":156,"name":"dorsal cochlear nucleus, fusiform and granule layer"},{"index":87,"red":197,"green":238,"blue":255,"name":"dorsal cochlear nucleus, deep core"},{"index":88,"red":255,"green":217,"blue":0,"name":"acoustic striae"},{"index":89,"red":213,"green":255,"blue":0,"name":"trapezoid body"},{"index":90,"red":0,"green":255,"blue":81,"name":"nucleus of the trapezoid body"},{"index":91,"red":0,"green":238,"blue":255,"name":"superior paraolivary nucleus"},{"index":92,"red":219,"green":239,"blue":61,"name":"medial superior olive"},{"index":93,"red":35,"green":76,"blue":190,"name":"lateral superior olive"},{"index":94,"red":1,"green":153,"blue":21,"name":"superior periolivary region"},{"index":95,"red":0,"green":174,"blue":255,"name":"ventral periolivary nuclei"},{"index":96,"red":255,"green":0,"blue":115,"name":"lateral lemniscus, ventral nucleus"},{"index":97,"red":171,"green":16,"blue":91,"name":"lateral lemniscus, intermediate nucleus"},{"index":98,"red":108,"green":18,"blue":91,"name":"lateral lemniscus, dorsal nucleus"},{"index":99,"red":255,"green":29,"blue":0,"name":"lateral lemniscus, commissure"},{"index":100,"red":255,"green":166,"blue":0,"name":"lateral lemniscus"},{"index":101,"red":206,"green":255,"blue":142,"name":"inferior colliculus, dorsal cortex"},{"index":102,"red":0,"green":238,"blue":255,"name":"inferior colliculus, central nucleus"},{"index":103,"red":48,"green":136,"blue":203,"name":"inferior colliculus, external cortex"},{"index":104,"red":176,"green":58,"blue":72,"name":"inferior colliculus, brachium"},{"index":105,"red":10,"green":244,"blue":217,"name":"medial geniculate body, medial division"},{"index":106,"red":239,"green":163,"blue":0,"name":"medial geniculate body, dorsal division"},{"index":107,"red":131,"green":58,"blue":31,"name":"medial geniculate body, ventral division"},{"index":108,"red":255,"green":47,"blue":242,"name":"medial geniculate body, marginal zone"},{"index":109,"red":255,"green":215,"blue":0,"name":"primary auditory cortex"},{"index":110,"red":240,"green":255,"blue":255,"name":"secondary auditory cortex, dorsal area"},{"index":111,"red":216,"green":191,"blue":216,"name":"secondary auditory cortex, ventral area"},{"index":112,"red":244,"green":156,"blue":255,"name":"auditory radiation"},{"index":113,"red":34,"green":152,"blue":255,"name":"ventral cochlear nucleus, anterior part"},{"index":114,"red":0,"green":230,"blue":207,"name":"ventral cochlear nucleus, posterior part"},{"index":115,"red":0,"green":255,"blue":106,"name":"ventral cochlear nucleus, cap area"},{"index":116,"red":185,"green":255,"blue":233,"name":"spiral ganglion"},{"index":117,"red":99,"green":205,"blue":0,"name":"nucleus sagulum"},{"index":118,"red":110,"green":0,"blue":255,"name":"reticular thalamic nucleus, auditory segment"}]